nofnof_filler_filler/.DS_Store
nofnof_filler_filler/__init__.py
nofnof_filler_filler/main.py
nofnof_filler_filler/src/.DS_Store
nofnof_filler_filler/src/__init__.py
nofnof_filler_filler/src/mapping.py
nofnof_filler_filler/src/noFillNoFuture.py
nofnof_filler_filler/src/token.py
nofnof_filler_filler-0.0.1.dist-info/WHEEL
nofnof_filler_filler-0.0.1.dist-info/METADATA
nofnof_filler_filler-0.0.1.dist-info/RECORD
